vlite_storage/__init__.py
vlite_storage/embedders.py
vlite_storage/storages.py
vlite_storage-0.1.0.dist-info/METADATA
vlite_storage-0.1.0.dist-info/WHEEL
vlite_storage-0.1.0.dist-info/top_level.txt
vlite_storage-0.1.0.dist-info/RECORD
