Metadata-Version: 2.1
Name: vlite-storage
Version: 0.1.0
Summary: Super simple vector data storage based on vectorlite
Author-email: Ivan Slepovichev <gurgutan@yandex.ru>
License: MIT
Requires-Python: >=3.11
Requires-Dist: vectorlite-py>=0.2.0
Requires-Dist: apsw>=3.47.2.0
Requires-Dist: numpy>=2.2.1
Requires-Dist: ollama>=0.4.4
